markdocpy/__init__.py
markdocpy/_docs.py
markdocpy/utils.py
markdocpy/version.py
markdocpy/ast/__init__.py
markdocpy/ast/function.py
markdocpy/ast/node.py
markdocpy/ast/tag.py
markdocpy/ast/variable.py
markdocpy/parser/__init__.py
markdocpy/parser/parser.py
markdocpy/parser/tag_parser.py
markdocpy/parser/tokenizer.py
markdocpy/renderer/__init__.py
markdocpy/renderer/html.py
markdocpy/schema/__init__.py
markdocpy/schema/functions.py
markdocpy/schema/nodes.py
markdocpy/schema/tags.py
markdocpy/schema_types/__init__.py
markdocpy/schema_types/class_type.py
markdocpy/schema_types/id_type.py
markdocpy/transform/__init__.py
markdocpy/transform/transformer.py
markdocpy/validator/__init__.py
markdocpy/validator/validator.py
markdoc_py-0.3.0.dist-info/METADATA
markdoc_py-0.3.0.dist-info/WHEEL
markdoc_py-0.3.0.dist-info/entry_points.txt
markdoc_py-0.3.0.dist-info/licenses/LICENSE
markdoc_py-0.3.0.dist-info/RECORD
