Metadata-Version: 2.4
Name: markdoc-py
Version: 0.3.0
Summary: Python port of Markdoc
Author-email: Oskar Skoog <oskar@osd.se>
License-Expression: MIT
License-File: LICENSE
Requires-Python: >=3.11
Requires-Dist: markdown-it-py>=4.0.0
Provides-Extra: dev
Requires-Dist: pdoc>=16.0.0; extra == 'dev'
Requires-Dist: pytest>=9.0.2; extra == 'dev'
Requires-Dist: ruff>=0.1.0; extra == 'dev'
Requires-Dist: tox>=4.0.0; extra == 'dev'
